__init__.py
osmdiff/__init__.py
osmdiff/augmenteddiff.py
osmdiff/config.py
osmdiff/osmchange.py
osmdiff/settings.py
osmdiff/osm/__init__.py
osmdiff/osm/osm.py
osmdiff-0.4.6.dist-info/licenses/LICENSE
osmdiff-0.4.6.dist-info/METADATA
osmdiff-0.4.6.dist-info/WHEEL
osmdiff-0.4.6.dist-info/top_level.txt
osmdiff-0.4.6.dist-info/RECORD
