Metadata-Version: 2.4
Name: osmdiff
Version: 0.4.6
Summary: A read-only interface to OpenStreetMap change APIs and files
Author-email: Martijn van Exel <m@rtijn.org>
Maintainer-email: Martijn van Exel <m@rtijn.org>
License-Expression: MIT
Project-URL: Homepage, https://github.com/mvexel/osmdiff
Project-URL: Bug Tracker, https://github.com/mvexel/osmdiff/issues
Keywords: openstreetmap,osm,diff,changeset,api
Classifier: Programming Language :: Python :: 3
Classifier: Operating System :: OS Independent
Requires-Python: >=3.9
License-File: LICENSE
Requires-Dist: python-dateutil>=2.9.0.post0
Requires-Dist: requests>=2.32.2
Dynamic: license-file
